verilog_basic_modules/adder.v
module adder (a, b, cin, sum, cout);

    input a;       
    input b;  
    input cin;  
    output sum;  
    output cout;  

    wire sum1, carry1, carry2;

    assign sum1 = a ^ b;      
    assign carry1 = a & b;   

    assign sum = sum1 ^ cin;   
    assign carry2 = sum1 & cin; 

    assign cout = carry1 | carry2; 

endmodule

verilog_basic_modules/adder_tb.v
`timescale 1ns / 1ns
`include "adder.v"

module adder_tb;

    reg a, b, cin;
    wire sum, cout;

   adder uut (a, b, cin, sum, cout);

   initial begin

        $dumpfile("adder_tb.vcd");
        $dumpvars(0, adder_tb);

        $monitor("a = %b, b = %b, cin = %b | sum = %b, cout = %b", a, b, cin, sum, cout);
        
        a = 0; b = 0; cin = 0; #10;
        a = 0; b = 0; cin = 1; #10;
        a = 0; b = 1; cin = 0; #10;
        a = 0; b = 1; cin = 1; #10;
        a = 1; b = 0; cin = 0; #10;
        a = 1; b = 0; cin = 1; #10;
        a = 1; b = 1; cin = 0; #10;
        a = 1; b = 1; cin = 1; #10;

        $display("test complete");
        $finish;

   end

endmodule

verilog_basic_modules/adder_tb.vcd
$date
	Tue Jul 01 22:44:33 2025
$end
$version
	Icarus Verilog
$end
$timescale
	1ns
$end
$scope module adder_tb $end
$var wire 1 ! sum $end
$var wire 1 " cout $end
$var reg 1 # a $end
$var reg 1 $ b $end
$var reg 1 % cin $end
$scope module uut $end
$var wire 1 # a $end
$var wire 1 $ b $end
$var wire 1 & carry1 $end
$var wire 1 ' carry2 $end
$var wire 1 % cin $end
$var wire 1 " cout $end
$var wire 1 ! sum $end
$var wire 1 ( sum1 $end
$upscope $end
$upscope $end
$enddefinitions $end
$comment Show the parameter values. $end
$dumpall
$end
#0
$dumpvars
0(
0'
0&
0%
0$
0#
0"
0!
$end
#10
1!
1%
#20
1(
0%
1$
#30
1"
0!
1'
1%
#40
0"
1!
0'
0%
0$
1#
#50
1"
0!
1'
1%
#60
0'
0(
1&
0%
1$
#70
1!
1%
