verilog_basic_modules/xor_ff.v
module xor_ff (
    input wire in,
    input wire clk,
    output reg out = 0
);
    wire xor_out;

    assign xor_out = in ^ out;

    always @(posedge clk) begin
        out <= xor_out;
    end

endmodule

verilog_basic_modules/xor_ff_tb.v
`timescale 1ns/1ns
`include "xor_ff.v"

module xor_ff_tb;

    reg in, clk;
    wire out;

    xor_ff uut (in, clk, out);

    // Clock generation
    initial begin
        clk = 0;
        forever #5 clk = ~clk;  // 10ns period clock
    end

    initial begin
        // Dump waves for GTKWave
        $dumpfile("xor_ff_tb.vcd");
        $dumpvars(0, xor_ff_tb);

        // Initialize input
        in = 0;
        #10;

        // Change input synchronized with clock edges
        @(posedge clk);
        in = 1;
        @(posedge clk);
        in = 0;
        @(posedge clk);
        in = 1;

        // Let the simulation run a few clock cycles to observe output changes
        repeat (5) @(posedge clk);

        $display("Test complete");
        $finish;
    end

    // Optional: monitor signals every time they change
    initial
        $monitor("Time=%0t | clk=%b in=%b out=%b", $time, clk, in, out);

endmodule

verilog_basic_modules/xor_ff_tb.vcd
$date
	Wed Jul 02 01:40:50 2025
$end
$version
	Icarus Verilog
$end
$timescale
	1ns
$end
$scope module xor_ff_tb $end
$var wire 1 ! out $end
$var reg 1 " clk $end
$var reg 1 # in $end
$scope module uut $end
$var wire 1 " clk $end
$var wire 1 # in $end
$var wire 1 $ xor_out $end
$var reg 1 ! out $end
$upscope $end
$upscope $end
$enddefinitions $end
$comment Show the parameter values. $end
$dumpall
$end
#0
$dumpvars
0$
0#
0"
0!
$end
#5
1"
#10
0"
#15
1$
1#
1"
#20
0"
#25
1!
1$
0#
1"
#30
0"
#35
0$
1#
1"
#40
0"
#45
1$
0!
1"
#50
0"
#55
0$
1!
1"
#60
0"
#65
1$
0!
1"
#70
0"
#75
0$
1!
1"
#80
0"
#85
1$
0!
1"
